egc/__init__.py
egc/config/AGC.yaml
egc/config/AGCN.yaml
egc/config/AGE.yaml
egc/config/ComE.yaml
egc/config/CommunityGAN.yaml
egc/config/DAEGC.yaml
egc/config/DANMF.yaml
egc/config/DFCN.yaml
egc/config/GALA.yaml
egc/config/GDCL.yaml
egc/config/MNMF.yaml
egc/config/MVGRL.yaml
egc/config/SDCN.yaml
egc/config/SEComm.yaml
egc/config/SENet_kmeans.yaml
egc/config/SUBLIME.yaml
egc/config/VGAECD.yaml
egc/config/cc.yaml
egc/config/clusternet.yaml
egc/config/dgi_kmeans.yaml
egc/config/gae_kmeans.yaml
egc/config/gmi_kmeans.yaml
egc/config/idec.yaml
egc/config/pca_kmeans.yaml
egc/config/sgc_kmeans.yaml
egc/config/vgae_kmeans.yaml
egc/model/__init__.py
egc/model/graph_clustering/__init__.py
egc/model/graph_clustering/base.py
egc/model/graph_clustering/disjoint/ComE.py
egc/model/graph_clustering/disjoint/SEComm.py
egc/model/graph_clustering/disjoint/SENet_kmeans.py
egc/model/graph_clustering/disjoint/__init__.py
egc/model/graph_clustering/disjoint/agc_kmeans.py
egc/model/graph_clustering/disjoint/agcn.py
egc/model/graph_clustering/disjoint/age_cluster.py
egc/model/graph_clustering/disjoint/cc.py
egc/model/graph_clustering/disjoint/clusternet.py
egc/model/graph_clustering/disjoint/daegc.py
egc/model/graph_clustering/disjoint/danmf.py
egc/model/graph_clustering/disjoint/dfcn.py
egc/model/graph_clustering/disjoint/dgc.py
egc/model/graph_clustering/disjoint/dgc_mlp.py
egc/model/graph_clustering/disjoint/dgc_mlp_gsl.py
egc/model/graph_clustering/disjoint/dgi_kmeans.py
egc/model/graph_clustering/disjoint/gae_kmeans.py
egc/model/graph_clustering/disjoint/gala.py
egc/model/graph_clustering/disjoint/gdcl.py
egc/model/graph_clustering/disjoint/gmi_kmeans.py
egc/model/graph_clustering/disjoint/idec.py
egc/model/graph_clustering/disjoint/mnmf.py
egc/model/graph_clustering/disjoint/pca_kmeans.py
egc/model/graph_clustering/disjoint/sdcn.py
egc/model/graph_clustering/disjoint/sgc_kmeans.py
egc/model/graph_clustering/disjoint/vgae_kmeans.py
egc/model/graph_clustering/disjoint/vgaecd.py
egc-0.3.0.dist-info/METADATA
egc-0.3.0.dist-info/WHEEL
egc-0.3.0.dist-info/licenses/LICENSE
egc-0.3.0.dist-info/RECORD
