Metadata-Version: 2.1
Name: egc
Version: 0.3.0
Summary: Benchmark of Graph Clustering.
Project-URL: Homepage, https://github.com/eaglelab-zju/EGC
Project-URL: Bug Tracker, https://github.com/eaglelab-zju/EGC/issues
Author-email: EAGLE-Lab <galo.gm.work@gmail.com>
License: MIT License
License-File: LICENSE
Keywords: community detection,graph,graph clustering
Classifier: License :: OSI Approved :: MIT License
Classifier: Programming Language :: Python :: 3
Classifier: Topic :: Software Development :: Libraries :: Python Modules
Requires-Python: >=3.8
Requires-Dist: cython>=3.0.5
Requires-Dist: dgl>=1.1.0
Requires-Dist: dglgo>=0.0.2
Requires-Dist: gdown>=4.7
Requires-Dist: seaborn>=0.13.0
Requires-Dist: texttable>=1.6
Requires-Dist: torch-geometric>=2.0
Requires-Dist: torch>=1.12
Requires-Dist: torchaudio>=0.10.2
Requires-Dist: torchvision>=0.11.3
Requires-Dist: wget>=3.2
